pybotchi/__init__.py
pybotchi/action.py
pybotchi/common.py
pybotchi/context.py
pybotchi/grpc/__init__.py
pybotchi/grpc/action.py
pybotchi/grpc/cli.py
pybotchi/grpc/common.py
pybotchi/grpc/context.py
pybotchi/grpc/exception.py
pybotchi/grpc/handler.py
pybotchi/grpc/pybotchi.proto
pybotchi/grpc/pybotchi_pb2.py
pybotchi/grpc/pybotchi_pb2.pyi
pybotchi/grpc/pybotchi_pb2_grpc.py
pybotchi/grpc/utils.py
pybotchi/llm.py
pybotchi/mcp/__init__.py
pybotchi/mcp/action.py
pybotchi/mcp/common.py
pybotchi/mcp/context.py
pybotchi/utils.py
pybotchi-3.0.4.dist-info/METADATA
pybotchi-3.0.4.dist-info/WHEEL
pybotchi-3.0.4.dist-info/entry_points.txt
pybotchi-3.0.4.dist-info/licenses/LICENSE
pybotchi-3.0.4.dist-info/RECORD
