Metadata-Version: 2.4
Name: pybotchi
Version: 3.0.4
Summary: A deterministic, intent-based AI agent builder.
License-File: LICENSE
Author: Alexie (Boyong) Madolid
Author-email: madolid.alexie@gmail.com
Requires-Python: >=3.12.0,<4.0
Classifier: Programming Language :: Python :: 3
Classifier: Programming Language :: Python :: 3.12
Classifier: Programming Language :: Python :: 3.13
Classifier: Programming Language :: Python :: 3.14
Provides-Extra: grpc
Provides-Extra: mcp
Requires-Dist: aiofiles (>=25.1.0) ; extra == "grpc"
Requires-Dist: click (>=8.3.1) ; extra == "grpc"
Requires-Dist: datamodel-code-generator (>=0.31.2) ; extra == "mcp" or extra == "grpc"
Requires-Dist: grpcio (>=1.76.0) ; extra == "grpc"
Requires-Dist: grpcio-tools (>=1.76.0) ; extra == "grpc"
Requires-Dist: langchain-core (>=0.3.15)
Requires-Dist: mcp (>=1.15.0) ; extra == "mcp"
Requires-Dist: orjson (>=3.9.11)
Requires-Dist: pydantic (>=2.0)
Project-URL: Repository, https://github.com/amadolid/pybotchi
